calculator/__init__.py
calculator/calculator_py_file.py
jawad_calculator-0.2.0.dist-info/licenses/LICENSE.txt
jawad_calculator-0.2.0.dist-info/METADATA
jawad_calculator-0.2.0.dist-info/WHEEL
jawad_calculator-0.2.0.dist-info/top_level.txt
jawad_calculator-0.2.0.dist-info/RECORD
