Metadata-Version: 2.4
Name: jawad_calculator
Version: 0.2.0
Summary: A simple calculator with addition and subtraction
Author-email: Jawad Iqbal <jawad.iqbal@somersetft.nhs.uk>
Classifier: Programming Language :: Python :: 3
Classifier: License :: OSI Approved :: MIT License
Requires-Python: >=3.8
License-File: LICENSE.txt
Dynamic: license-file
